koolstof/__init__.py
koolstof/airica.py
koolstof/coulometer.py
koolstof/crm.py
koolstof/meta.py
koolstof/misc.py
koolstof/molar.py
koolstof/optode.py
koolstof/parameterisations.py
koolstof/quaatro.py
koolstof/infrared/__init__.py
koolstof/infrared/baseline.py
koolstof/infrared/io.py
koolstof/plot/__init__.py
koolstof/plot/profiles.py
koolstof/spectro/__init__.py
koolstof/spectro/oxygen.py
koolstof/vindta/__init__.py
koolstof/vindta/get.py
koolstof/vindta/plot.py
koolstof/vindta/process.py
koolstof/vindta/read.py
koolstof-0.31.dist-info/LICENSE
koolstof-0.31.dist-info/METADATA
koolstof-0.31.dist-info/WHEEL
koolstof-0.31.dist-info/top_level.txt
koolstof-0.31.dist-info/RECORD
